Examples/__init__.py
Examples/General_Example/__init__.py
Examples/General_Example/evolutionaryProcess.py
Examples/General_Example/evolutionaryProcess_v1.py
Examples/MazeGen_Generator/ScenarioBuilder.py
Examples/MazeGen_Generator/__init__.py
Examples/MazeGen_Generator/fitnessFunction.py
Examples/MazeGen_Generator/fitnessFunctionv1.py
Examples/MazeGen_Generator/main.py
Examples/MazeGen_Generator/run-v1.py
Examples/MazeGen_Generator/run-v2.py
Examples/MazeGen_Generator/run.py
Examples/Python_Classify/FitnessFunction.py
Examples/Python_Classify/__init__.py
Examples/Python_Classify/fitnesFunctionTest.py
Examples/Python_Classify/run.py
Examples/Python_Pi/__init__.py
Examples/Python_Pi/fitnessFunction.py
Examples/Python_Pi/run.py
Examples/Python_PrimesN/__init__.py
Examples/Python_PrimesN/fitnessFunction.py
Examples/Python_PrimesN/run.py
Examples/Python_Trading/__init__.py
Examples/Python_Trading/fitnesFunction.py
Examples/Python_Trading/historicalCripto.py
Examples/Python_Trading/run.py
Examples/Python_Trading/runs.py
Examples/Python_Trading/testPhenotype.py
Examples/Python_Trading/testRealPhenotype.py
core/__init__.py
core/domain/Individual.py
core/domain/__init__.py
core/domain/algorithms.py
core/domain/generalFunctions.py
core/domain/grammarWrapper.py
core/domain/mapper.py
core/domain/population.py
core/fitnessFunctions/__init__.py
core/fitnessFunctions/generalsFunctions.py
core/fitnessFunctions/syntheticFunctions.py
core/searchOperators/__init__.py
core/searchOperators/gaCore.py
tests/__init__.py
tests/grammarContainer.py
tests/test_grammarWrapper.py
tests/test_mapper.py
tests/test_searchOperators.py
utils_/__init__.py
utils_/algorithms.py
PyGEVO-0.0.2.dist-info/LICENSE
PyGEVO-0.0.2.dist-info/METADATA
PyGEVO-0.0.2.dist-info/WHEEL
PyGEVO-0.0.2.dist-info/top_level.txt
PyGEVO-0.0.2.dist-info/RECORD
