Metadata-Version: 2.1
Name: PyGEVO
Version: 0.0.2
Summary: The package for PyGEVO
Home-page: https://github.com/IvanHGuevara/PyGE
Author: Ivan Guevara & Lucas Gonzalez
Author-email: ivan.hugo.guevara@gmail.com
License: UNKNOWN
Platform: UNKNOWN
Classifier: Programming Language :: Python :: 3
Classifier: License :: OSI Approved :: MIT License
Classifier: Operating System :: OS Independent
Requires-Python: >=3.5
License-File: LICENSE
Requires-Dist: apscheduler (==3.7.0)
Requires-Dist: Cython (==0.29.22)
Requires-Dist: dateparser (==1.0.0)
Requires-Dist: gevent (==21.1.2)
Requires-Dist: matplotlib (==3.3.3)
Requires-Dist: pathlib (==1.0.1)
Requires-Dist: pytz (==2020.1)
Requires-Dist: ta (==0.7.0)
Requires-Dist: tabulate (==0.8.7)
Requires-Dist: websocket-client (==0.58.0)
Requires-Dist: cachetools (==4.2.2)
Requires-Dist: numpy (==1.19.1)
Requires-Dist: pandas (==1.1.3)
Requires-Dist: requests (==2.24.0)
Requires-Dist: setuptools (==54.1.1)
